xunter.py
xunter-0.2.3.data/scripts/xunter
xunter-0.2.3.data/scripts/xunter2excel
xunter-0.2.3.dist-info/LICENSE
xunter-0.2.3.dist-info/METADATA
xunter-0.2.3.dist-info/WHEEL
xunter-0.2.3.dist-info/top_level.txt
xunter-0.2.3.dist-info/RECORD
