Metadata-Version: 2.1
Name: xunter
Version: 0.2.3
Summary: Profiling for the xonsh shell based on hunter.
Home-page: https://github.com/anki-code/xunter
Author: anki-code
Author-email: no@no.no
License: MIT
Project-URL: Documentation, https://github.com/anki-code/xunter/blob/master/README.md
Project-URL: Code, https://github.com/anki-code/xunter
Project-URL: Issue tracker, https://github.com/anki-code/xunter/issues
Platform: any
Classifier: Programming Language :: Python :: 3
Classifier: Programming Language :: Python :: 3.6
Classifier: Programming Language :: Python :: 3.7
Classifier: Programming Language :: Python :: 3.8
Classifier: Programming Language :: Python :: 3.9
Classifier: License :: OSI Approved :: MIT License
Classifier: Operating System :: OS Independent
Classifier: Topic :: System :: Shells
Classifier: Topic :: System :: System Shells
Classifier: Topic :: Terminals
Requires-Python: >=3.6
License-File: LICENSE
Requires-Dist: xonsh
Requires-Dist: hunter
